Metadata-Version: 2.4
Name: cursofiap-package-leojosantos
Version: 1.0.0
Summary: Descricao da sua lib cursofiap
Home-page: https://github.com/leojosants
Author: Leonardo Oliveira
Author-email: leonardojosantos@gmail.com
License: MIT
License-File: LICENSE
Dynamic: author
Dynamic: author-email
Dynamic: description
Dynamic: description-content-type
Dynamic: home-page
Dynamic: license
Dynamic: license-file
Dynamic: summary
